[
  {
    "type": "event",
    "anonymous": false,
    "name": "Swap",
    "inputs": [
      {"indexed": true,  "internalType": "address", "name": "sender",     "type": "address"},
      {"indexed": false, "internalType": "uint256", "name": "amount0In",  "type": "uint256"},
      {"indexed": false, "internalType": "uint256", "name": "amount1In",  "type": "uint256"},
      {"indexed": false, "internalType": "uint256", "name": "amount0Out", "type": "uint256"},
      {"indexed": false, "internalType": "uint256", "name": "amount1Out", "type": "uint256"},
      {"indexed": true,  "internalType": "address", "name": "to",         "type": "address"}
    ]
  },
  {
    "type": "event",
    "anonymous": false,
    "name": "Mint",
    "inputs": [
      {"indexed": true,  "internalType": "address", "name": "sender",  "type": "address"},
      {"indexed": false, "internalType": "uint256", "name": "amount0", "type": "uint256"},
      {"indexed": false, "internalType": "uint256", "name": "amount1", "type": "uint256"}
    ]
  },
  {
    "type": "event",
    "anonymous": false,
    "name": "Burn",
    "inputs": [
      {"indexed": true,  "internalType": "address", "name": "sender",  "type": "address"},
      {"indexed": false, "internalType": "uint256", "name": "amount0", "type": "uint256"},
      {"indexed": false, "internalType": "uint256", "name": "amount1", "type": "uint256"},
      {"indexed": true,  "internalType": "address", "name": "to",      "type": "address"}
    ]
  },
  {
    "type": "event",
    "anonymous": false,
    "name": "Sync",
    "inputs": [
      {"indexed": false, "internalType": "uint112", "name": "reserve0", "type": "uint112"},
      {"indexed": false, "internalType": "uint112", "name": "reserve1", "type": "uint112"}
    ]
  }
]


